{"GlobalPropertiesHash":"ZSurk3BtublTfzAnbNGd9qbEZKEVyUjjbGboGkqsM9w=","FingerprintPatternsHash":"gq3WsqcKBUGTSNle7RKKyXRIwh7M8ccEqOqYvIzoM04=","PropertyOverridesHash":"8ZRc1sGeVrPBx4lD717BgRaQekyh78QKV9SKsdt638U=","InputHashes":["jTgMc5WRLqMk\u002BEx65T1dPWIcmK2QwFsliXX7HnMAf7o=","V/8jrPJRSrK5GuRLLFjARxbPXC8EBgSY19JegYBVAd4=","AXjHda/2teu8nEHV1fDeBBKoHK32IW4fWtR7B9f91m4=","tT\u002B09O/3oB4no0Eb\u002B2Sp6XfWas8dnQT2rFxtwnwVduc=","rl18g2cy\u002BBq5trSVjN2UeyI\u002BvpoGlfRhK5JTvDrQTXE=","N6AMvR1sTe22//I2jCO9OetVC9JDk08w0vUq99pqjgY=","WGMQNRBqniInO9EN9kCLNBR7Tmz48wpn2P5EnzIf//w="],"CachedAssets":{"jTgMc5WRLqMk\u002BEx65T1dPWIcmK2QwFsliXX7HnMAf7o=":{"Identity":"C:\\Users\\Usuario\\Downloads\\SelenneApi\\SelenneApi\\wwwroot\\uploads\\25e8fb9b-e7ce-4458-9968-df7d7c339c74.png","SourceId":"SelenneApi","SourceType":"Discovered","ContentRoot":"C:\\Users\\Usuario\\Downloads\\SelenneApi\\SelenneApi\\wwwroot\\","BasePath":"/","RelativePath":"uploads/25e8fb9b-e7ce-4458-9968-df7d7c339c74#[.{fingerprint}]?.png","AssetKind":"All","AssetMode":"All","AssetRole":"Primary","AssetMergeBehavior":null,"AssetMergeSource":"","RelatedAsset":null,"AssetTraitName":null,"AssetTraitValue":null,"Fingerprint":"ucbn5bsk6t","Integrity":"wnXd6YC/zXecO5KPsNy6NotD7QLyNbW8RZAniFLi0bs=","CopyToOutputDirectory":"Never","CopyToPublishDirectory":"PreserveNewest","OriginalItemSpec":"wwwroot\\uploads\\25e8fb9b-e7ce-4458-9968-df7d7c339c74.png","FileLength":1982382,"LastWriteTime":"2026-03-10T02:09:12.9744678+00:00"},"V/8jrPJRSrK5GuRLLFjARxbPXC8EBgSY19JegYBVAd4=":{"Identity":"C:\\Users\\Usuario\\Downloads\\SelenneApi\\SelenneApi\\wwwroot\\uploads\\3fbb0a65-349f-47ef-89ec-599f52b0e8b3.jpg","SourceId":"SelenneApi","SourceType":"Discovered","ContentRoot":"C:\\Users\\Usuario\\Downloads\\SelenneApi\\SelenneApi\\wwwroot\\","BasePath":"/","RelativePath":"uploads/3fbb0a65-349f-47ef-89ec-599f52b0e8b3#[.{fingerprint}]?.jpg","AssetKind":"All","AssetMode":"All","AssetRole":"Primary","AssetMergeBehavior":null,"AssetMergeSource":"","RelatedAsset":null,"AssetTraitName":null,"AssetTraitValue":null,"Fingerprint":"xnmqr53fpr","Integrity":"w\u002Bubl6akoNrGAJldErbfnt2CvEgxQdR08sNXWwmWxh0=","CopyToOutputDirectory":"Never","CopyToPublishDirectory":"PreserveNewest","OriginalItemSpec":"wwwroot\\uploads\\3fbb0a65-349f-47ef-89ec-599f52b0e8b3.jpg","FileLength":13135,"LastWriteTime":"2026-03-16T13:21:05.0991134+00:00"},"AXjHda/2teu8nEHV1fDeBBKoHK32IW4fWtR7B9f91m4=":{"Identity":"C:\\Users\\Usuario\\Downloads\\SelenneApi\\SelenneApi\\wwwroot\\uploads\\64497eab-32e5-4d8f-ab7c-5093bb585402.jpg","SourceId":"SelenneApi","SourceType":"Discovered","ContentRoot":"C:\\Users\\Usuario\\Downloads\\SelenneApi\\SelenneApi\\wwwroot\\","BasePath":"/","RelativePath":"uploads/64497eab-32e5-4d8f-ab7c-5093bb585402#[.{fingerprint}]?.jpg","AssetKind":"All","AssetMode":"All","AssetRole":"Primary","AssetMergeBehavior":null,"AssetMergeSource":"","RelatedAsset":null,"AssetTraitName":null,"AssetTraitValue":null,"Fingerprint":"er59i58jew","Integrity":"lrTBl28UIgSbyFzGSUqsjM1skheHflMua02Plr\u002BnWyM=","CopyToOutputDirectory":"Never","CopyToPublishDirectory":"PreserveNewest","OriginalItemSpec":"wwwroot\\uploads\\64497eab-32e5-4d8f-ab7c-5093bb585402.jpg","FileLength":7002,"LastWriteTime":"2026-03-16T13:22:20.5221225+00:00"},"tT\u002B09O/3oB4no0Eb\u002B2Sp6XfWas8dnQT2rFxtwnwVduc=":{"Identity":"C:\\Users\\Usuario\\Downloads\\SelenneApi\\SelenneApi\\wwwroot\\uploads\\78d44cf2-6969-4883-8a25-a5b584e0dcc4.png","SourceId":"SelenneApi","SourceType":"Discovered","ContentRoot":"C:\\Users\\Usuario\\Downloads\\SelenneApi\\SelenneApi\\wwwroot\\","BasePath":"/","RelativePath":"uploads/78d44cf2-6969-4883-8a25-a5b584e0dcc4#[.{fingerprint}]?.png","AssetKind":"All","AssetMode":"All","AssetRole":"Primary","AssetMergeBehavior":null,"AssetMergeSource":"","RelatedAsset":null,"AssetTraitName":null,"AssetTraitValue":null,"Fingerprint":"c3u3p0ksvi","Integrity":"GLQ2bf4PB8Ib/2EXBIOCAFQ0ygGlPbwad0u/4wI4EGg=","CopyToOutputDirectory":"Never","CopyToPublishDirectory":"PreserveNewest","OriginalItemSpec":"wwwroot\\uploads\\78d44cf2-6969-4883-8a25-a5b584e0dcc4.png","FileLength":1521339,"LastWriteTime":"2026-03-10T12:10:41.4983232+00:00"},"rl18g2cy\u002BBq5trSVjN2UeyI\u002BvpoGlfRhK5JTvDrQTXE=":{"Identity":"C:\\Users\\Usuario\\Downloads\\SelenneApi\\SelenneApi\\wwwroot\\uploads\\bdbea41a-6533-4dbd-bfb8-5f835de74d95.jpg","SourceId":"SelenneApi","SourceType":"Discovered","ContentRoot":"C:\\Users\\Usuario\\Downloads\\SelenneApi\\SelenneApi\\wwwroot\\","BasePath":"/","RelativePath":"uploads/bdbea41a-6533-4dbd-bfb8-5f835de74d95#[.{fingerprint}]?.jpg","AssetKind":"All","AssetMode":"All","AssetRole":"Primary","AssetMergeBehavior":null,"AssetMergeSource":"","RelatedAsset":null,"AssetTraitName":null,"AssetTraitValue":null,"Fingerprint":"c5vjofpe8l","Integrity":"cOhwiJWlky0GT5cWmAAsXr8LN\u002BgGUdJgDFtPNz8ln/I=","CopyToOutputDirectory":"Never","CopyToPublishDirectory":"PreserveNewest","OriginalItemSpec":"wwwroot\\uploads\\bdbea41a-6533-4dbd-bfb8-5f835de74d95.jpg","FileLength":5509,"LastWriteTime":"2026-03-17T01:22:46.3070091+00:00"}},"CachedCopyCandidates":{}}